[
  {
    "First Name": "Ajay",
    "Middle Name": "",
    "Last Name": "Yadav",
    "Email": "Ajayyadav@gmail.com",
    "Secondary Email 1": "",
    "Phone Number": 8393809454,
    "Secondary Phone 1": "",
    "Enrollment Numbar": 135001,
    "Degree": "Post-Graduate",
    "Department": "Master Of Computer  Application",
    "Address": "A/505, IDPL Virbhadra Rishikesh Dehradun UK",
    "Designation": "",
    "Company": "",
    "Year Of Passing": 2016,
    "Year Of Joining": 2013,
    "Sub_ Institute": ""
  },
  {
    "First Name": "Akanksha",
    "Middle Name": "",
    "Last Name": "",
    "Email": "akku.semwal162@gmail.com",
    "Secondary Email 1": "",
    "Phone Number": 9412117538,
    "Secondary Phone 1": "",
    "Enrollment Numbar": 135002,
    "Degree": "Post-Graduate",
    "Department": "Master Of Computer  Application",
    "Address": "Sachidanand Nagar Near GIC Road Rudraprayag UK",
    "Designation": "",
    "Company": "",
    "Year Of Passing": 2016,
    "Year Of Joining": 2013,
    "Sub_ Institute": ""
  },
  {
    "First Name": "Amit",
    "Middle Name": "",
    "Last Name": "Kumar",
    "Email": "amitsati1993@gmail.com",
    "Secondary Email 1": "",
    "Phone Number": 9536277962,
    "Secondary Phone 1": 9720043296,
    "Enrollment Numbar": 135003,
    "Degree": "Post-Graduate",
    "Department": "Master Of Computer  Application",
    "Address": "12/10, Canel Road  Jakhan Rajpur Road Dehradun UK",
    "Designation": "",
    "Company": "",
    "Year Of Passing": 2016,
    "Year Of Joining": 2013,
    "Sub_ Institute": ""
  },
  {
    "First Name": "Anchal",
    "Middle Name": "",
    "Last Name": "Rawat",
    "Email": "aanchal752@gmail.com",
    "Secondary Email 1": "",
    "Phone Number": 9411361007,
    "Secondary Phone 1": 7579258501,
    "Enrollment Numbar": 135004,
    "Degree": "Post-Graduate",
    "Department": "Master Of Computer  Application",
    "Address": "Amrakunj Bugani Road Srinagar Garhwal UK",
    "Designation": "",
    "Company": "",
    "Year Of Passing": 2016,
    "Year Of Joining": 2013,
    "Sub_ Institute": ""
  },
  {
    "First Name": "Anil",
    "Middle Name": "",
    "Last Name": "Pokhariyal",
    "Email": "anilpokhiriyal1@gmail.com",
    "Secondary Email 1": "",
    "Phone Number": 9675517098,
    "Secondary Phone 1": 9917256401,
    "Enrollment Numbar": 135005,
    "Degree": "Post-Graduate",
    "Department": "Master Of Computer  Application",
    "Address": "Vill- Gorakhpur,  Po- Badowala Arkedia Grant Premnagar Dehradun UK",
    "Designation": "",
    "Company": "",
    "Year Of Passing": 2016,
    "Year Of Joining": 2013,
    "Sub_ Institute": ""
  },
  {
    "First Name": "Anuj",
    "Middle Name": "",
    "Last Name": "Kumar",
    "Email": "anujkamboj317@gmail.com",
    "Secondary Email 1": "",
    "Phone Number": 8449463808,
    "Secondary Phone 1": "",
    "Enrollment Numbar": 135006,
    "Degree": "Post-Graduate",
    "Department": "Master Of Computer  Application",
    "Address": "Kachnal Gosai Kashipur  USN UK",
    "Designation": "",
    "Company": "",
    "Year Of Passing": 2016,
    "Year Of Joining": 2013,
    "Sub_ Institute": ""
  },
  {
    "First Name": "Ashish",
    "Middle Name": "",
    "Last Name": "Pokhriyal",
    "Email": "",
    "Secondary Email 1": "",
    "Phone Number": 7895882421,
    "Secondary Phone 1": 955739280,
    "Enrollment Numbar": 135007,
    "Degree": "Post-Graduate",
    "Department": "Master Of Computer  Application",
    "Address": "Lane.No-  7, OM Vihar  Dharampur D.Dun UK",
    "Designation": "",
    "Company": "",
    "Year Of Passing": 2016,
    "Year Of Joining": 2013,
    "Sub_ Institute": ""
  },
  {
    "First Name": "Ashish",
    "Middle Name": "",
    "Last Name": "Sundriyal",
    "Email": "ashusundriyal56@gmail.com",
    "Secondary Email 1": "",
    "Phone Number": 9411043488,
    "Secondary Phone 1": "",
    "Enrollment Numbar": 135008,
    "Degree": "Post-Graduate",
    "Department": "Master Of Computer  Application",
    "Address": "C-82, New Colony  Kalagarh Kotdwara UK",
    "Designation": "",
    "Company": "",
    "Year Of Passing": 2016,
    "Year Of Joining": 2013,
    "Sub_ Institute": ""
  },
  {
    "First Name": "Ashok",
    "Middle Name": "",
    "Last Name": "Khatri",
    "Email": "ashokkhatri28@gmail.com",
    "Secondary Email 1": "",
    "Phone Number": 8057786908,
    "Secondary Phone 1": "",
    "Enrollment Numbar": 135009,
    "Degree": "Post-Graduate",
    "Department": "Master Of Computer  Application",
    "Address": "Near Swami  Omkaranand School Srikot  Ganganali Srinagar Garhwal UK",
    "Designation": "",
    "Company": "",
    "Year Of Passing": 2016,
    "Year Of Joining": 2013,
    "Sub_ Institute": ""
  },
  {
    "First Name": "Ayushay",
    "Middle Name": "",
    "Last Name": "Keshyal",
    "Email": "keshyal.ayushay@gmail.com",
    "Secondary Email 1": "",
    "Phone Number": 7351364789,
    "Secondary Phone 1": "",
    "Enrollment Numbar": 135010,
    "Degree": "Post-Graduate",
    "Department": "Master Of Computer  Application",
    "Address": "PWD   Colony Giwain Shrot  Kotdwara UK",
    "Designation": "",
    "Company": "",
    "Year Of Passing": 2016,
    "Year Of Joining": 2013,
    "Sub_ Institute": ""
  },
  {
    "First Name": "Divyani",
    "Middle Name": "",
    "Last Name": "Pant",
    "Email": "divyanipant17@gmail.com",
    "Secondary Email 1": "",
    "Phone Number": 9411975443,
    "Secondary Phone 1": "",
    "Enrollment Numbar": 135011,
    "Degree": "Post-Graduate",
    "Department": "Master Of Computer  Application",
    "Address": "Mohalla  Makeri Almora UK",
    "Designation": "",
    "Company": "",
    "Year Of Passing": 2016,
    "Year Of Joining": 2013,
    "Sub_ Institute": ""
  },
  {
    "First Name": "Eti",
    "Middle Name": "",
    "Last Name": "Bhardwaj",
    "Email": "eti.bhardwaj1503@gmail.com",
    "Secondary Email 1": "",
    "Phone Number": 9458374490,
    "Secondary Phone 1": 9411341578,
    "Enrollment Numbar": 135012,
    "Degree": "Post-Graduate",
    "Department": "Master Of Computer  Application",
    "Address": "Noida Secter -15,, E - 138,  UP",
    "Designation": "",
    "Company": "",
    "Year Of Passing": 2016,
    "Year Of Joining": 2013,
    "Sub_ Institute": ""
  },
  {
    "First Name": "Jagriti",
    "Middle Name": "",
    "Last Name": "Khanthwal",
    "Email": "jagritikhantwal@gmail.com",
    "Secondary Email 1": "",
    "Phone Number": 7417768330,
    "Secondary Phone 1": "",
    "Enrollment Numbar": 135013,
    "Degree": "Post-Graduate",
    "Department": "Master Of Computer  Application",
    "Address": "Manpur Near Shiv Mandir Kotdwara UK",
    "Designation": "",
    "Company": "",
    "Year Of Passing": 2016,
    "Year Of Joining": 2013,
    "Sub_ Institute": ""
  },
  {
    "First Name": "Jitesh",
    "Middle Name": "",
    "Last Name": "Kothari",
    "Email": "jiteshkothari10@gmail.com",
    "Secondary Email 1": "",
    "Phone Number": 9997621369,
    "Secondary Phone 1": 8755228858,
    "Enrollment Numbar": 135014,
    "Degree": "Post-Graduate",
    "Department": "Master Of Computer  Application",
    "Address": "4  Shastri Nagar  Haridwar Road Near Rispana  Bridge Dehradun  UK",
    "Designation": "",
    "Company": "",
    "Year Of Passing": 2016,
    "Year Of Joining": 2013,
    "Sub_ Institute": ""
  },
  {
    "First Name": "Kamaldeep",
    "Middle Name": "Singh",
    "Last Name": "Jagwan",
    "Email": "",
    "Secondary Email 1": "",
    "Phone Number": 9557561516,
    "Secondary Phone 1": "",
    "Enrollment Numbar": 135015,
    "Degree": "Post-Graduate",
    "Department": "Master Of Computer  Application",
    "Address": "Vill- Sandan, Post- Rudraprayag  Distt- Rudraprayag  UK",
    "Designation": "",
    "Company": "",
    "Year Of Passing": 2016,
    "Year Of Joining": 2013,
    "Sub_ Institute": ""
  },
  {
    "First Name": "Komal",
    "Middle Name": "",
    "Last Name": "Chandola",
    "Email": "komalchandola25@gmail.com",
    "Secondary Email 1": "",
    "Phone Number": 8979161289,
    "Secondary Phone 1": "",
    "Enrollment Numbar": 135016,
    "Degree": "Post-Graduate",
    "Department": "Master Of Computer  Application",
    "Address": "165, Bharat Vihar Line No- 2,  Near Rishi Gas Agency Rishikesh UK",
    "Designation": "",
    "Company": "",
    "Year Of Passing": 2016,
    "Year Of Joining": 2013,
    "Sub_ Institute": ""
  },
  {
    "First Name": "Lalit",
    "Middle Name": "Kumar",
    "Last Name": "Ravi",
    "Email": "hk59431@gmail.com",
    "Secondary Email 1": "",
    "Phone Number": 8439869596,
    "Secondary Phone 1": "",
    "Enrollment Numbar": 135017,
    "Degree": "Post-Graduate",
    "Department": "Master Of Computer  Application",
    "Address": "Indra Vihar Colony Sunhara Road Road Behind Micron  Factry Roorkee UK",
    "Designation": "",
    "Company": "",
    "Year Of Passing": 2016,
    "Year Of Joining": 2013,
    "Sub_ Institute": ""
  },
  {
    "First Name": "Manoj",
    "Middle Name": "",
    "Last Name": "Kumar",
    "Email": "monojch2991@gmail.com",
    "Secondary Email 1": "",
    "Phone Number": 9756754647,
    "Secondary Phone 1": "",
    "Enrollment Numbar": 135018,
    "Degree": "Post-Graduate",
    "Department": "Master Of Computer  Application",
    "Address": "Vill-  Ram Pur, Raighty  Post- Bhikkam Jeet  Pur Haridwar UK",
    "Designation": "",
    "Company": "",
    "Year Of Passing": 2016,
    "Year Of Joining": 2013,
    "Sub_ Institute": ""
  },
  {
    "First Name": "Mohd.",
    "Middle Name": "",
    "Last Name": "Mursleen",
    "Email": "mursleen.mohd009@gmail.com",
    "Secondary Email 1": "",
    "Phone Number": 9045817699,
    "Secondary Phone 1": "",
    "Enrollment Numbar": 135019,
    "Degree": "Post-Graduate",
    "Department": "Master Of Computer  Application",
    "Address": "Mohalla Dilla Singh Monu Conf Jaspur U S Nagar Uttrakhand UK",
    "Designation": "",
    "Company": "",
    "Year Of Passing": 2016,
    "Year Of Joining": 2013,
    "Sub_ Institute": ""
  },
  {
    "First Name": "Mohit",
    "Middle Name": "",
    "Last Name": "Rawat",
    "Email": "love.rawat94@gmail.com",
    "Secondary Email 1": "",
    "Phone Number": 9897772499,
    "Secondary Phone 1": "",
    "Enrollment Numbar": 135020,
    "Degree": "Post-Graduate",
    "Department": "Master Of Computer  Application",
    "Address": "Negi Colony Ranjha  Wala Raipur  Dehradun UK",
    "Designation": "",
    "Company": "",
    "Year Of Passing": 2016,
    "Year Of Joining": 2013,
    "Sub_ Institute": ""
  },
  {
    "First Name": "Neha",
    "Middle Name": "",
    "Last Name": "Pundir",
    "Email": "nehapundir71@gmail.com",
    "Secondary Email 1": "",
    "Phone Number": 8755683258,
    "Secondary Phone 1": "",
    "Enrollment Numbar": 135021,
    "Degree": "Post-Graduate",
    "Department": "Master Of Computer  Application",
    "Address": "Upper Rajiv Nagar Post- Nehru  Gram Dharampur Danda D.Dun  UK",
    "Designation": "",
    "Company": "",
    "Year Of Passing": 2016,
    "Year Of Joining": 2013,
    "Sub_ Institute": ""
  },
  {
    "First Name": "Nutan",
    "Middle Name": "",
    "Last Name": "",
    "Email": "sr76820@gmail.com",
    "Secondary Email 1": "",
    "Phone Number": 7895437770,
    "Secondary Phone 1": 9045372536,
    "Enrollment Numbar": 135022,
    "Degree": "Post-Graduate",
    "Department": "Master Of Computer  Application",
    "Address": "Vill- Garighat Chak No-1, Tehsil Kotdwar Dist- Pauri  Garhwal UK",
    "Designation": "",
    "Company": "",
    "Year Of Passing": 2016,
    "Year Of Joining": 2013,
    "Sub_ Institute": ""
  },
  {
    "First Name": "Poonam",
    "Middle Name": "",
    "Last Name": "Saklani",
    "Email": "pnmsaklani59@gmail.com",
    "Secondary Email 1": "",
    "Phone Number": 7830228769,
    "Secondary Phone 1": 9411183019,
    "Enrollment Numbar": 135023,
    "Degree": "Post-Graduate",
    "Department": "Master Of Computer  Application",
    "Address": "Vill+Post- Mayali  Distt- Rudraprayag  UK",
    "Designation": "",
    "Company": "",
    "Year Of Passing": 2016,
    "Year Of Joining": 2013,
    "Sub_ Institute": ""
  },
  {
    "First Name": "Pratyaksh",
    "Middle Name": "",
    "Last Name": "Rajput",
    "Email": "Partyakkshaeil@gmail.com",
    "Secondary Email 1": "",
    "Phone Number": 9758886219,
    "Secondary Phone 1": 9759599177,
    "Enrollment Numbar": 135024,
    "Degree": "Post-Graduate",
    "Department": "Master Of Computer  Application",
    "Address": "Near Lokesh Dham  C/O Ram  Goppal Chauhan  Pahari  Bazar  Kankhal Haridwar UK",
    "Designation": "",
    "Company": "",
    "Year Of Passing": 2016,
    "Year Of Joining": 2013,
    "Sub_ Institute": ""
  },
  {
    "First Name": "Priyanka",
    "Middle Name": "",
    "Last Name": "Bhatt",
    "Email": "prriyangel009@gmail.com",
    "Secondary Email 1": "",
    "Phone Number": 9456574174,
    "Secondary Phone 1": 9927404751,
    "Enrollment Numbar": 135025,
    "Degree": "Post-Graduate",
    "Department": "Master Of Computer  Application",
    "Address": "Near Abhy Medical Store Dugal  Khola Almora UK",
    "Designation": "",
    "Company": "",
    "Year Of Passing": 2016,
    "Year Of Joining": 2013,
    "Sub_ Institute": ""
  },
  {
    "First Name": "Rajesh",
    "Middle Name": "",
    "Last Name": "Rana",
    "Email": "rajeshrana41@gmail.com",
    "Secondary Email 1": "",
    "Phone Number": 9719689465,
    "Secondary Phone 1": "",
    "Enrollment Numbar": 135026,
    "Degree": "Post-Graduate",
    "Department": "Master Of Computer  Application",
    "Address": "180, Chandreswar  Marg Maya  Kund Rishikesh UK - 249201",
    "Designation": "",
    "Company": "",
    "Year Of Passing": 2016,
    "Year Of Joining": 2013,
    "Sub_ Institute": ""
  },
  {
    "First Name": "Rashmi",
    "Middle Name": "",
    "Last Name": "Thapliyal",
    "Email": "Rashamithapliyal91@gmail.com",
    "Secondary Email 1": "",
    "Phone Number": 9411382991,
    "Secondary Phone 1": 9997086023,
    "Enrollment Numbar": 135027,
    "Degree": "Post-Graduate",
    "Department": "Master Of Computer  Application",
    "Address": "Lane.No- 6, Ganesh Vihar Ajabpur  Khurd  Dehradun UK",
    "Designation": "",
    "Company": "",
    "Year Of Passing": 2016,
    "Year Of Joining": 2013,
    "Sub_ Institute": ""
  },
  {
    "First Name": "Sachin",
    "Middle Name": "",
    "Last Name": "Kumar",
    "Email": "prajapatisachin@gmail.com",
    "Secondary Email 1": "",
    "Phone Number": 8859893557,
    "Secondary Phone 1": "",
    "Enrollment Numbar": 135028,
    "Degree": "Post-Graduate",
    "Department": "Master Of Computer  Application",
    "Address": "Vill- Bhandura, Post- Jat Muzhera, Distt- Muzzaffer Nagar UP",
    "Designation": "",
    "Company": "",
    "Year Of Passing": 2016,
    "Year Of Joining": 2013,
    "Sub_ Institute": ""
  },
  {
    "First Name": "Shivani",
    "Middle Name": "",
    "Last Name": "Negi",
    "Email": "ishilpashivani@gmail.com",
    "Secondary Email 1": "",
    "Phone Number": 9450174019,
    "Secondary Phone 1": "",
    "Enrollment Numbar": 135029,
    "Degree": "Post-Graduate",
    "Department": "Master Of Computer  Application",
    "Address": "Vill-Nandpur, Post- Padampur, Motadhar Kotdwar Pauri Garhwal UK",
    "Designation": "",
    "Company": "",
    "Year Of Passing": 2016,
    "Year Of Joining": 2013,
    "Sub_ Institute": ""
  },
  {
    "First Name": "Subham",
    "Middle Name": "",
    "Last Name": "Pokhriyal",
    "Email": "www.shubhampokhriyal50@gmail.com",
    "Secondary Email 1": "",
    "Phone Number": 8859702828,
    "Secondary Phone 1": "",
    "Enrollment Numbar": 135030,
    "Degree": "Post-Graduate",
    "Department": "Master Of Computer  Application",
    "Address": "Near  Bal Vidhya Niketan School  Sitabpur Kotdwar UK",
    "Designation": "",
    "Company": "",
    "Year Of Passing": 2016,
    "Year Of Joining": 2013,
    "Sub_ Institute": ""
  },
  {
    "First Name": "Shubhangi",
    "Middle Name": "",
    "Last Name": "Kumud",
    "Email": "shubhangi02@gmail.com",
    "Secondary Email 1": "",
    "Phone Number": 8265992102,
    "Secondary Phone 1": "",
    "Enrollment Numbar": 135031,
    "Degree": "Post-Graduate",
    "Department": "Master Of Computer  Application",
    "Address": "149, Gandhi Printing House  Latowali  Kankhal Haridwar  UK",
    "Designation": "",
    "Company": "",
    "Year Of Passing": 2016,
    "Year Of Joining": 2013,
    "Sub_ Institute": ""
  },
  {
    "First Name": "Suraj",
    "Middle Name": "",
    "Last Name": "Negi",
    "Email": "surajshine36@gmail.com",
    "Secondary Email 1": "",
    "Phone Number": 8006643325,
    "Secondary Phone 1": 7417521469,
    "Enrollment Numbar": 135032,
    "Degree": "Post-Graduate",
    "Department": "Master Of Computer  Application",
    "Address": "Shivrajpur Durga  Puri Kotdwar _ Pin Code- 246149",
    "Designation": "",
    "Company": "",
    "Year Of Passing": 2016,
    "Year Of Joining": 2013,
    "Sub_ Institute": ""
  },
  {
    "First Name": "Sushmita",
    "Middle Name": "",
    "Last Name": "",
    "Email": "pundirsushmita3@gmail.com",
    "Secondary Email 1": "",
    "Phone Number": 7830684854,
    "Secondary Phone 1": "",
    "Enrollment Numbar": 135033,
    "Degree": "Post-Graduate",
    "Department": "Master Of Computer  Application",
    "Address": "Akash Deep Emporium  Main Market Agastyamuni Rudrraprayag UK",
    "Designation": "",
    "Company": "",
    "Year Of Passing": 2016,
    "Year Of Joining": 2013,
    "Sub_ Institute": ""
  },
  {
    "First Name": "Tej Prakash",
    "Middle Name": "Singh",
    "Last Name": "Rana",
    "Email": "tejsingh072@gmail.com",
    "Secondary Email 1": "",
    "Phone Number": 7895099599,
    "Secondary Phone 1": "",
    "Enrollment Numbar": 135034,
    "Degree": "Post-Graduate",
    "Department": "Master Of Computer  Application",
    "Address": "C/o DL Bhatt  Johnpur Kotdwar  UK",
    "Designation": "",
    "Company": "",
    "Year Of Passing": 2016,
    "Year Of Joining": 2013,
    "Sub_ Institute": ""
  },
  {
    "First Name": "Vikash",
    "Middle Name": "",
    "Last Name": "Patwal",
    "Email": "vikashpatwal46@gmail.com",
    "Secondary Email 1": "",
    "Phone Number": 8859746370,
    "Secondary Phone 1": 7060230083,
    "Enrollment Numbar": 135035,
    "Degree": "Post-Graduate",
    "Department": "Master Of Computer  Application",
    "Address": "Vill- Kochiyar PO- Dhumakot, Pauri Garhwal UK",
    "Designation": "",
    "Company": "",
    "Year Of Passing": 2016,
    "Year Of Joining": 2013,
    "Sub_ Institute": ""
  },
  {
    "First Name": "Vikshit",
    "Middle Name": "",
    "Last Name": "Dhyani",
    "Email": "vikshit9292@gmail.com",
    "Secondary Email 1": "",
    "Phone Number": 7417126797,
    "Secondary Phone 1": "",
    "Enrollment Numbar": 135036,
    "Degree": "Post-Graduate",
    "Department": "Master Of Computer  Application",
    "Address": "Vill- Lalpur, Po- Padampur Sukhrow Distt-  Pauri Garhwal Uttrakhand",
    "Designation": "",
    "Company": "",
    "Year Of Passing": 2016,
    "Year Of Joining": 2013,
    "Sub_ Institute": ""
  },
  {
    "First Name": "Vipin",
    "Middle Name": "",
    "Last Name": "Pokhriyal",
    "Email": "pokhriyal93vipin@gmail.com",
    "Secondary Email 1": "",
    "Phone Number": 9627115851,
    "Secondary Phone 1": 9456152922,
    "Enrollment Numbar": 135037,
    "Degree": "Post-Graduate",
    "Department": "Master Of Computer  Application",
    "Address": "Behind Base Hospital Colony Srikot Srinagar UK",
    "Designation": "",
    "Company": "",
    "Year Of Passing": 2016,
    "Year Of Joining": 2013,
    "Sub_ Institute": ""
  }
]